openapi_client/__init__.py
openapi_client/api_client.py
openapi_client/api_response.py
openapi_client/configuration.py
openapi_client/exceptions.py
openapi_client/py.typed
openapi_client/rest.py
openapi_client/api/__init__.py
openapi_client/api/check_name_servers_api.py
openapi_client/api/dns_record_api.py
openapi_client/api/zone_api.py
openapi_client/models/__init__.py
openapi_client/models/all_dns_record_response.py
openapi_client/models/create_zone.py
openapi_client/models/create_zone_request.py
openapi_client/models/dns_record.py
openapi_client/models/dns_record_id.py
openapi_client/models/dns_record_response.py
openapi_client/models/submitted.py
openapi_client/models/zone.py
openapi_client/models/zones.py
jarqvi_test-1.0.0.dist-info/METADATA
jarqvi_test-1.0.0.dist-info/WHEEL
jarqvi_test-1.0.0.dist-info/top_level.txt
jarqvi_test-1.0.0.dist-info/RECORD
