Metadata-Version: 2.1
Name: jarqvi-test
Version: 1.0.0
Summary: DNS
Home-page: UNKNOWN
Author: OpenAPI Generator community
Author-email: info@liara.ir
License: UNKNOWN
Keywords: OpenAPI,OpenAPI-Generator,DNS
Platform: UNKNOWN
Requires-Dist: aenum
Requires-Dist: pydantic >=2
Requires-Dist: python-dateutil
Requires-Dist: typing-extensions >=4.7.1
Requires-Dist: urllib3 <2.1.0,>=1.25.3
